Metadata-Version: 1.2
Name: arabic-reshaper-fork
Version: 2.0.14
Summary: Reconstruct Arabic sentences to be used in applications that don't support Arabic
Home-page: https://mpcabd.xyz/python-arabic-text-reshaper/
Author: Abdullah Diab
Author-email: mpcabd@gmail.com
Maintainer: Abdullah Diab
Maintainer-email: mpcabd@gmail.com
License: GPL
Download-URL: https://github.com/mpcabd/python-arabic-reshaper/tarball/master
Keywords: arabic shaping reshaping reshaper
Platform: ALL
Classifier: Natural Language :: Arabic
Classifier: Operating System :: OS Independent
Classifier: Programming Language :: Python :: 2.7
Classifier: Programming Language :: Python :: 3.5
Classifier: Programming Language :: Python :: 3.6
Classifier: Topic :: Software Development :: Libraries :: Python Modules
